{
  "_meta": {
    "description": "Registry of discovered PriceRunner DK category IDs. Updated as new categories are verified.",
    "lastUpdated": "2026-05-22",
    "treeDiscovery": {
      "method": "navigation/menu endpoint",
      "note": "Tree is essentially static. Scrape once, cache indefinitely.",
      "reference": "docs/pricerunner-api-reference.md"
    }
  },
  "topics": {
    "t34": {
      "name": "Hjem & Husholdning",
      "verified": true,
      "leafCategories": [
        "cl1617", "cl90", "cl84", "cl69", "cl10025", "cl81", "cl10027", "cl104",
        "cl250", "cl479", "cl83", "cl621", "cl82", "cl10023", "cl248", "cl249",
        "cl10024", "cl10022", "cl10020", "cl10026", "cl1244", "cl88", "cl1312",
        "cl85", "cl333", "cl10021", "cl68",
        "cl21", "cl3", "cl13", "cl1613", "cl19", "cl212", "cl715", "cl740", "cl17", "cl14",
        "cl516", "cl10038", "cl528", "cl484", "cl453", "cl456", "cl10031", "cl1274",
        "cl589", "cl628", "cl70", "cl80", "cl550", "cl590", "cl357", "cl401", "cl1404"
      ]
    },
    "t1424": {
      "name": "Have & Udemiljø",
      "verified": true,
      "leafCategories": [
        "cl1595", "cl335", "cl659", "cl120", "cl519", "cl119", "cl347",
        "cl638", "cl348", "cl499", "cl1467", "cl504", "cl1611", "cl541",
        "cl1388", "cl10018", "cl1593"
      ]
    }
  },
  "categories": {
    "14": {
      "name": "Vaskemaskiner",
      "slug": "vaskemaskiner",
      "verified": true,
      "discoveredAt": "2026-05-22",
      "parentPath": ["34:Hjem & Husholdning", "3:Hvidevarer", "14:Vaskemaskiner"]
    },
    "81": {
      "name": "Frituregryder & Airfryere",
      "slug": "frituregryder-airfryere",
      "verified": true,
      "discoveredAt": "2026-05-22",
      "parentPath": ["34:Hjem & Husholdning", "14:Køkkenapparater", "81:Frituregryder & Airfryere"]
    },
    "82": {
      "name": "Kaffemaskiner",
      "slug": "kaffemaskiner",
      "verified": true,
      "discoveredAt": "2026-05-22",
      "parentPath": ["34:Hjem & Husholdning", "14:Køkkenapparater", "82:Kaffemaskiner"]
    },
    "120": {
      "name": "Havemaskiner",
      "slug": "havemaskiner",
      "verified": true,
      "discoveredAt": "2026-05-22",
      "parentPath": ["1424:Have & Udemiljø", "120:Havemaskiner"]
    },
    "1595": {
      "name": "Robotplæneklippere",
      "slug": "robotplaeneklippere",
      "verified": true,
      "discoveredAt": "2026-05-22",
      "parentPath": ["1424:Have & Udemiljø", "1595:Robotplæneklippere"]
    },
    "1613": {
      "name": "Robotstøvsugere",
      "slug": "robotstoevsugere",
      "verified": true,
      "discoveredAt": "2026-05-07",
      "parentPath": ["34:Hjem & Husholdning", "3:Hvidevarer", "1613:Robotstøvsugere"]
    },
    "250": {
      "name": "Ismaskiner",
      "slug": "ismaskiner",
      "verified": true,
      "discoveredAt": "2026-05-22",
      "parentPath": ["34:Hjem & Husholdning", "14:Køkkenapparater", "250:Ismaskiner"]
    },
    "335": {
      "name": "Grill",
      "slug": "grill",
      "verified": true,
      "discoveredAt": "2026-05-22",
      "parentPath": ["1424:Have & Udemiljø", "335:Grill"]
    },
    "345": {
      "name": "Elværktøj",
      "slug": "elvaerktoej",
      "verified": true,
      "discoveredAt": "2026-05-22",
      "parentPath": ["182:Renovering & Byggeri", "1492:Værktøj & Maskiner", "345:Elværktøj"]
    },
    "638": {
      "name": "Højtryks- & Hedvandsrensere",
      "slug": "hojtryks-hedvandsrensere",
      "verified": true,
      "discoveredAt": "2026-05-22",
      "parentPath": ["1424:Have & Udemiljø", "638:Højtryks- & Hedvandsrensere"]
    },
    "1258": {
      "name": "Bore- & Skruemaskiner",
      "slug": "bore-skruemaskiner",
      "verified": true,
      "discoveredAt": "2026-05-22",
      "parentPath": ["182:Renovering & Byggeri", "1492:Værktøj & Maskiner", "1258:Bore- & Skruemaskiner"]
    },
    "1260": {
      "name": "Elsave",
      "slug": "elsave",
      "verified": true,
      "discoveredAt": "2026-05-22",
      "parentPath": ["182:Renovering & Byggeri", "1492:Værktøj & Maskiner", "1260:Elsave"]
    }
  },
  "pending": {
    "1607": {
      "name": "Køleskabe",
      "slug": "koeleskabe",
      "verified": false,
      "note": "ID from guess, needs verification"
    },
    "1605": {
      "name": "Opvaskemaskiner",
      "slug": "opvaskemaskiner",
      "verified": false,
      "note": "ID from guess, needs verification"
    }
  }
}
